{
    "version": "1.23.15",
    "notificationList": [],
    "monitorList": [
        {
            "id": 1,
            "name": "KES-BIS",
            "description": null,
            "pathName": "KES-BIS",
            "parent": null,
            "childrenIDs": [],
            "url": "http://106.13.28.81:88/",
            "method": "GET",
            "hostname": null,
            "port": null,
            "maxretries": 0,
            "weight": 2000,
            "active": true,
            "forceInactive": false,
            "type": "http",
            "timeout": 48,
            "interval": 60,
            "retryInterval": 60,
            "resendInterval": 0,
            "keyword": null,
            "invertKeyword": false,
            "expiryNotification": false,
            "ignoreTls": false,
            "upsideDown": false,
            "packetSize": 56,
            "maxredirects": 10,
            "accepted_statuscodes": [
                "200-299"
            ],
            "dns_resolve_type": "A",
            "dns_resolve_server": "1.1.1.1",
            "dns_last_result": null,
            "docker_container": "",
            "docker_host": null,
            "proxyId": null,
            "notificationIDList": {},
            "tags": [],
            "maintenance": false,
            "mqttTopic": "",
            "mqttSuccessMessage": "",
            "databaseQuery": null,
            "authMethod": null,
            "grpcUrl": null,
            "grpcProtobuf": null,
            "grpcMethod": null,
            "grpcServiceName": null,
            "grpcEnableTls": false,
            "radiusCalledStationId": null,
            "radiusCallingStationId": null,
            "game": null,
            "gamedigGivenPortOnly": true,
            "httpBodyEncoding": "json",
            "jsonPath": null,
            "expectedValue": null,
            "kafkaProducerTopic": null,
            "kafkaProducerBrokers": [],
            "kafkaProducerSsl": false,
            "kafkaProducerAllowAutoTopicCreation": false,
            "kafkaProducerMessage": null,
            "screenshot": null,
            "headers": null,
            "body": null,
            "grpcBody": null,
            "grpcMetadata": null,
            "basic_auth_user": null,
            "basic_auth_pass": null,
            "oauth_client_id": null,
            "oauth_client_secret": null,
            "oauth_token_url": null,
            "oauth_scopes": null,
            "oauth_auth_method": "client_secret_basic",
            "pushToken": null,
            "databaseConnectionString": null,
            "radiusUsername": null,
            "radiusPassword": null,
            "radiusSecret": null,
            "mqttUsername": "",
            "mqttPassword": "",
            "authWorkstation": null,
            "authDomain": null,
            "tlsCa": null,
            "tlsCert": null,
            "tlsKey": null,
            "kafkaProducerSaslOptions": {
                "mechanism": "None"
            },
            "includeSensitiveData": true
        },
        {
            "id": 2,
            "name": "KES-KES",
            "description": null,
            "pathName": "KES-KES",
            "parent": null,
            "childrenIDs": [],
            "url": "http://106.13.28.81/",
            "method": "GET",
            "hostname": null,
            "port": null,
            "maxretries": 0,
            "weight": 2000,
            "active": true,
            "forceInactive": false,
            "type": "http",
            "timeout": 48,
            "interval": 60,
            "retryInterval": 60,
            "resendInterval": 0,
            "keyword": null,
            "invertKeyword": false,
            "expiryNotification": false,
            "ignoreTls": false,
            "upsideDown": false,
            "packetSize": 56,
            "maxredirects": 10,
            "accepted_statuscodes": [
                "200-299"
            ],
            "dns_resolve_type": "A",
            "dns_resolve_server": "1.1.1.1",
            "dns_last_result": null,
            "docker_container": "",
            "docker_host": null,
            "proxyId": null,
            "notificationIDList": {},
            "tags": [],
            "maintenance": false,
            "mqttTopic": "",
            "mqttSuccessMessage": "",
            "databaseQuery": null,
            "authMethod": null,
            "grpcUrl": null,
            "grpcProtobuf": null,
            "grpcMethod": null,
            "grpcServiceName": null,
            "grpcEnableTls": false,
            "radiusCalledStationId": null,
            "radiusCallingStationId": null,
            "game": null,
            "gamedigGivenPortOnly": true,
            "httpBodyEncoding": "json",
            "jsonPath": null,
            "expectedValue": null,
            "kafkaProducerTopic": null,
            "kafkaProducerBrokers": [],
            "kafkaProducerSsl": false,
            "kafkaProducerAllowAutoTopicCreation": false,
            "kafkaProducerMessage": null,
            "screenshot": null,
            "headers": null,
            "body": null,
            "grpcBody": null,
            "grpcMetadata": null,
            "basic_auth_user": null,
            "basic_auth_pass": null,
            "oauth_client_id": null,
            "oauth_client_secret": null,
            "oauth_token_url": null,
            "oauth_scopes": null,
            "oauth_auth_method": "client_secret_basic",
            "pushToken": null,
            "databaseConnectionString": null,
            "radiusUsername": null,
            "radiusPassword": null,
            "radiusSecret": null,
            "mqttUsername": "",
            "mqttPassword": "",
            "authWorkstation": null,
            "authDomain": null,
            "tlsCa": null,
            "tlsCert": null,
            "tlsKey": null,
            "kafkaProducerSaslOptions": {
                "mechanism": "None"
            },
            "includeSensitiveData": true
        },
        {
            "id": 3,
            "name": "KES-SUPPLY",
            "description": null,
            "pathName": "KES-SUPPLY",
            "parent": null,
            "childrenIDs": [],
            "url": "http://106.13.28.81:90/",
            "method": "GET",
            "hostname": null,
            "port": null,
            "maxretries": 0,
            "weight": 2000,
            "active": true,
            "forceInactive": false,
            "type": "http",
            "timeout": 48,
            "interval": 60,
            "retryInterval": 60,
            "resendInterval": 0,
            "keyword": null,
            "invertKeyword": false,
            "expiryNotification": false,
            "ignoreTls": false,
            "upsideDown": false,
            "packetSize": 56,
            "maxredirects": 10,
            "accepted_statuscodes": [
                "200-299"
            ],
            "dns_resolve_type": "A",
            "dns_resolve_server": "1.1.1.1",
            "dns_last_result": null,
            "docker_container": "",
            "docker_host": null,
            "proxyId": null,
            "notificationIDList": {},
            "tags": [],
            "maintenance": false,
            "mqttTopic": "",
            "mqttSuccessMessage": "",
            "databaseQuery": null,
            "authMethod": null,
            "grpcUrl": null,
            "grpcProtobuf": null,
            "grpcMethod": null,
            "grpcServiceName": null,
            "grpcEnableTls": false,
            "radiusCalledStationId": null,
            "radiusCallingStationId": null,
            "game": null,
            "gamedigGivenPortOnly": true,
            "httpBodyEncoding": "json",
            "jsonPath": null,
            "expectedValue": null,
            "kafkaProducerTopic": null,
            "kafkaProducerBrokers": [],
            "kafkaProducerSsl": false,
            "kafkaProducerAllowAutoTopicCreation": false,
            "kafkaProducerMessage": null,
            "screenshot": null,
            "headers": null,
            "body": null,
            "grpcBody": null,
            "grpcMetadata": null,
            "basic_auth_user": null,
            "basic_auth_pass": null,
            "oauth_client_id": null,
            "oauth_client_secret": null,
            "oauth_token_url": null,
            "oauth_scopes": null,
            "oauth_auth_method": "client_secret_basic",
            "pushToken": null,
            "databaseConnectionString": null,
            "radiusUsername": null,
            "radiusPassword": null,
            "radiusSecret": null,
            "mqttUsername": "",
            "mqttPassword": "",
            "authWorkstation": null,
            "authDomain": null,
            "tlsCa": null,
            "tlsCert": null,
            "tlsKey": null,
            "kafkaProducerSaslOptions": {
                "mechanism": "None"
            },
            "includeSensitiveData": true
        },
        {
            "id": 4,
            "name": "XXLJOB-调度器",
            "description": null,
            "pathName": "XXLJOB-调度器",
            "parent": null,
            "childrenIDs": [],
            "url": "http://106.13.28.81:8080/xxl-job-admin/",
            "method": "GET",
            "hostname": null,
            "port": null,
            "maxretries": 0,
            "weight": 2000,
            "active": true,
            "forceInactive": false,
            "type": "http",
            "timeout": 48,
            "interval": 60,
            "retryInterval": 60,
            "resendInterval": 0,
            "keyword": null,
            "invertKeyword": false,
            "expiryNotification": false,
            "ignoreTls": false,
            "upsideDown": false,
            "packetSize": 56,
            "maxredirects": 10,
            "accepted_statuscodes": [
                "200-299"
            ],
            "dns_resolve_type": "A",
            "dns_resolve_server": "1.1.1.1",
            "dns_last_result": null,
            "docker_container": "",
            "docker_host": null,
            "proxyId": null,
            "notificationIDList": {},
            "tags": [],
            "maintenance": false,
            "mqttTopic": "",
            "mqttSuccessMessage": "",
            "databaseQuery": null,
            "authMethod": null,
            "grpcUrl": null,
            "grpcProtobuf": null,
            "grpcMethod": null,
            "grpcServiceName": null,
            "grpcEnableTls": false,
            "radiusCalledStationId": null,
            "radiusCallingStationId": null,
            "game": null,
            "gamedigGivenPortOnly": true,
            "httpBodyEncoding": "json",
            "jsonPath": null,
            "expectedValue": null,
            "kafkaProducerTopic": null,
            "kafkaProducerBrokers": [],
            "kafkaProducerSsl": false,
            "kafkaProducerAllowAutoTopicCreation": false,
            "kafkaProducerMessage": null,
            "screenshot": null,
            "headers": null,
            "body": null,
            "grpcBody": null,
            "grpcMetadata": null,
            "basic_auth_user": null,
            "basic_auth_pass": null,
            "oauth_client_id": null,
            "oauth_client_secret": null,
            "oauth_token_url": null,
            "oauth_scopes": null,
            "oauth_auth_method": "client_secret_basic",
            "pushToken": null,
            "databaseConnectionString": null,
            "radiusUsername": null,
            "radiusPassword": null,
            "radiusSecret": null,
            "mqttUsername": "",
            "mqttPassword": "",
            "authWorkstation": null,
            "authDomain": null,
            "tlsCa": null,
            "tlsCert": null,
            "tlsKey": null,
            "kafkaProducerSaslOptions": {
                "mechanism": "None"
            },
            "includeSensitiveData": true
        },
        {
            "id": 5,
            "name": "XXLJOB-执行器1",
            "description": null,
            "pathName": "XXLJOB-执行器1",
            "parent": null,
            "childrenIDs": [],
            "url": "http://106.13.28.81:9001/",
            "method": "GET",
            "hostname": null,
            "port": null,
            "maxretries": 0,
            "weight": 2000,
            "active": true,
            "forceInactive": false,
            "type": "http",
            "timeout": 48,
            "interval": 60,
            "retryInterval": 60,
            "resendInterval": 0,
            "keyword": null,
            "invertKeyword": false,
            "expiryNotification": false,
            "ignoreTls": false,
            "upsideDown": false,
            "packetSize": 56,
            "maxredirects": 10,
            "accepted_statuscodes": [
                "200-299"
            ],
            "dns_resolve_type": "A",
            "dns_resolve_server": "1.1.1.1",
            "dns_last_result": null,
            "docker_container": "",
            "docker_host": null,
            "proxyId": null,
            "notificationIDList": {},
            "tags": [],
            "maintenance": false,
            "mqttTopic": "",
            "mqttSuccessMessage": "",
            "databaseQuery": null,
            "authMethod": null,
            "grpcUrl": null,
            "grpcProtobuf": null,
            "grpcMethod": null,
            "grpcServiceName": null,
            "grpcEnableTls": false,
            "radiusCalledStationId": null,
            "radiusCallingStationId": null,
            "game": null,
            "gamedigGivenPortOnly": true,
            "httpBodyEncoding": "json",
            "jsonPath": null,
            "expectedValue": null,
            "kafkaProducerTopic": null,
            "kafkaProducerBrokers": [],
            "kafkaProducerSsl": false,
            "kafkaProducerAllowAutoTopicCreation": false,
            "kafkaProducerMessage": null,
            "screenshot": null,
            "headers": null,
            "body": null,
            "grpcBody": null,
            "grpcMetadata": null,
            "basic_auth_user": null,
            "basic_auth_pass": null,
            "oauth_client_id": null,
            "oauth_client_secret": null,
            "oauth_token_url": null,
            "oauth_scopes": null,
            "oauth_auth_method": "client_secret_basic",
            "pushToken": null,
            "databaseConnectionString": null,
            "radiusUsername": null,
            "radiusPassword": null,
            "radiusSecret": null,
            "mqttUsername": "",
            "mqttPassword": "",
            "authWorkstation": null,
            "authDomain": null,
            "tlsCa": null,
            "tlsCert": null,
            "tlsKey": null,
            "kafkaProducerSaslOptions": {
                "mechanism": "None"
            },
            "includeSensitiveData": true
        },
        {
            "id": 6,
            "name": "官网-KESHOME",
            "description": null,
            "pathName": "官网-KESHOME",
            "parent": null,
            "childrenIDs": [],
            "url": "https://www.keshome.com/",
            "method": "GET",
            "hostname": null,
            "port": null,
            "maxretries": 0,
            "weight": 2000,
            "active": true,
            "forceInactive": false,
            "type": "http",
            "timeout": 48,
            "interval": 60,
            "retryInterval": 60,
            "resendInterval": 0,
            "keyword": null,
            "invertKeyword": false,
            "expiryNotification": false,
            "ignoreTls": false,
            "upsideDown": false,
            "packetSize": 56,
            "maxredirects": 10,
            "accepted_statuscodes": [
                "200-299"
            ],
            "dns_resolve_type": "A",
            "dns_resolve_server": "1.1.1.1",
            "dns_last_result": null,
            "docker_container": "",
            "docker_host": null,
            "proxyId": null,
            "notificationIDList": {},
            "tags": [],
            "maintenance": false,
            "mqttTopic": "",
            "mqttSuccessMessage": "",
            "databaseQuery": null,
            "authMethod": null,
            "grpcUrl": null,
            "grpcProtobuf": null,
            "grpcMethod": null,
            "grpcServiceName": null,
            "grpcEnableTls": false,
            "radiusCalledStationId": null,
            "radiusCallingStationId": null,
            "game": null,
            "gamedigGivenPortOnly": true,
            "httpBodyEncoding": "json",
            "jsonPath": null,
            "expectedValue": null,
            "kafkaProducerTopic": null,
            "kafkaProducerBrokers": [],
            "kafkaProducerSsl": false,
            "kafkaProducerAllowAutoTopicCreation": false,
            "kafkaProducerMessage": null,
            "screenshot": null,
            "headers": null,
            "body": null,
            "grpcBody": null,
            "grpcMetadata": null,
            "basic_auth_user": null,
            "basic_auth_pass": null,
            "oauth_client_id": null,
            "oauth_client_secret": null,
            "oauth_token_url": null,
            "oauth_scopes": null,
            "oauth_auth_method": "client_secret_basic",
            "pushToken": null,
            "databaseConnectionString": null,
            "radiusUsername": null,
            "radiusPassword": null,
            "radiusSecret": null,
            "mqttUsername": "",
            "mqttPassword": "",
            "authWorkstation": null,
            "authDomain": null,
            "tlsCa": null,
            "tlsCert": null,
            "tlsKey": null,
            "kafkaProducerSaslOptions": {
                "mechanism": "None"
            },
            "includeSensitiveData": true
        },
        {
            "id": 7,
            "name": "XXLJOB-执行器2",
            "description": null,
            "pathName": "XXLJOB-执行器2",
            "parent": null,
            "childrenIDs": [],
            "url": "http://106.13.28.81:9999/",
            "method": "GET",
            "hostname": null,
            "port": null,
            "maxretries": 0,
            "weight": 2000,
            "active": true,
            "forceInactive": false,
            "type": "http",
            "timeout": 48,
            "interval": 60,
            "retryInterval": 60,
            "resendInterval": 0,
            "keyword": null,
            "invertKeyword": false,
            "expiryNotification": false,
            "ignoreTls": false,
            "upsideDown": false,
            "packetSize": 56,
            "maxredirects": 10,
            "accepted_statuscodes": [
                "200-299"
            ],
            "dns_resolve_type": "A",
            "dns_resolve_server": "1.1.1.1",
            "dns_last_result": null,
            "docker_container": "",
            "docker_host": null,
            "proxyId": null,
            "notificationIDList": {},
            "tags": [],
            "maintenance": false,
            "mqttTopic": "",
            "mqttSuccessMessage": "",
            "databaseQuery": null,
            "authMethod": null,
            "grpcUrl": null,
            "grpcProtobuf": null,
            "grpcMethod": null,
            "grpcServiceName": null,
            "grpcEnableTls": false,
            "radiusCalledStationId": null,
            "radiusCallingStationId": null,
            "game": null,
            "gamedigGivenPortOnly": true,
            "httpBodyEncoding": "json",
            "jsonPath": null,
            "expectedValue": null,
            "kafkaProducerTopic": null,
            "kafkaProducerBrokers": [],
            "kafkaProducerSsl": false,
            "kafkaProducerAllowAutoTopicCreation": false,
            "kafkaProducerMessage": null,
            "screenshot": null,
            "headers": null,
            "body": null,
            "grpcBody": null,
            "grpcMetadata": null,
            "basic_auth_user": null,
            "basic_auth_pass": null,
            "oauth_client_id": null,
            "oauth_client_secret": null,
            "oauth_token_url": null,
            "oauth_scopes": null,
            "oauth_auth_method": "client_secret_basic",
            "pushToken": null,
            "databaseConnectionString": null,
            "radiusUsername": null,
            "radiusPassword": null,
            "radiusSecret": null,
            "mqttUsername": "",
            "mqttPassword": "",
            "authWorkstation": null,
            "authDomain": null,
            "tlsCa": null,
            "tlsCert": null,
            "tlsKey": null,
            "kafkaProducerSaslOptions": {
                "mechanism": "None"
            },
            "includeSensitiveData": true
        },
        {
            "id": 8,
            "name": "官网-KESINK",
            "description": null,
            "pathName": "官网-KESINK",
            "parent": null,
            "childrenIDs": [],
            "url": "https://www.kesink.net/chat",
            "method": "GET",
            "hostname": null,
            "port": null,
            "maxretries": 0,
            "weight": 2000,
            "active": true,
            "forceInactive": false,
            "type": "http",
            "timeout": 48,
            "interval": 60,
            "retryInterval": 60,
            "resendInterval": 0,
            "keyword": null,
            "invertKeyword": false,
            "expiryNotification": false,
            "ignoreTls": false,
            "upsideDown": false,
            "packetSize": 56,
            "maxredirects": 10,
            "accepted_statuscodes": [
                "200-299"
            ],
            "dns_resolve_type": "A",
            "dns_resolve_server": "1.1.1.1",
            "dns_last_result": null,
            "docker_container": "",
            "docker_host": null,
            "proxyId": null,
            "notificationIDList": {},
            "tags": [],
            "maintenance": false,
            "mqttTopic": "",
            "mqttSuccessMessage": "",
            "databaseQuery": null,
            "authMethod": null,
            "grpcUrl": null,
            "grpcProtobuf": null,
            "grpcMethod": null,
            "grpcServiceName": null,
            "grpcEnableTls": false,
            "radiusCalledStationId": null,
            "radiusCallingStationId": null,
            "game": null,
            "gamedigGivenPortOnly": true,
            "httpBodyEncoding": "json",
            "jsonPath": null,
            "expectedValue": null,
            "kafkaProducerTopic": null,
            "kafkaProducerBrokers": [],
            "kafkaProducerSsl": false,
            "kafkaProducerAllowAutoTopicCreation": false,
            "kafkaProducerMessage": null,
            "screenshot": null,
            "headers": null,
            "body": null,
            "grpcBody": null,
            "grpcMetadata": null,
            "basic_auth_user": null,
            "basic_auth_pass": null,
            "oauth_client_id": null,
            "oauth_client_secret": null,
            "oauth_token_url": null,
            "oauth_scopes": null,
            "oauth_auth_method": "client_secret_basic",
            "pushToken": null,
            "databaseConnectionString": null,
            "radiusUsername": null,
            "radiusPassword": null,
            "radiusSecret": null,
            "mqttUsername": "",
            "mqttPassword": "",
            "authWorkstation": null,
            "authDomain": null,
            "tlsCa": null,
            "tlsCert": null,
            "tlsKey": null,
            "kafkaProducerSaslOptions": {
                "mechanism": "None"
            },
            "includeSensitiveData": true
        },
        {
            "id": 9,
            "name": "官网-solution帮助页面",
            "description": null,
            "pathName": "官网-solution帮助页面",
            "parent": null,
            "childrenIDs": [],
            "url": "https://keshomesolutions.com/",
            "method": "GET",
            "hostname": null,
            "port": null,
            "maxretries": 0,
            "weight": 2000,
            "active": true,
            "forceInactive": false,
            "type": "http",
            "timeout": 48,
            "interval": 60,
            "retryInterval": 60,
            "resendInterval": 0,
            "keyword": null,
            "invertKeyword": false,
            "expiryNotification": false,
            "ignoreTls": false,
            "upsideDown": false,
            "packetSize": 56,
            "maxredirects": 10,
            "accepted_statuscodes": [
                "200-299"
            ],
            "dns_resolve_type": "A",
            "dns_resolve_server": "1.1.1.1",
            "dns_last_result": null,
            "docker_container": "",
            "docker_host": null,
            "proxyId": null,
            "notificationIDList": {},
            "tags": [],
            "maintenance": false,
            "mqttTopic": "",
            "mqttSuccessMessage": "",
            "databaseQuery": null,
            "authMethod": null,
            "grpcUrl": null,
            "grpcProtobuf": null,
            "grpcMethod": null,
            "grpcServiceName": null,
            "grpcEnableTls": false,
            "radiusCalledStationId": null,
            "radiusCallingStationId": null,
            "game": null,
            "gamedigGivenPortOnly": true,
            "httpBodyEncoding": "json",
            "jsonPath": null,
            "expectedValue": null,
            "kafkaProducerTopic": null,
            "kafkaProducerBrokers": [],
            "kafkaProducerSsl": false,
            "kafkaProducerAllowAutoTopicCreation": false,
            "kafkaProducerMessage": null,
            "screenshot": null,
            "headers": null,
            "body": null,
            "grpcBody": null,
            "grpcMetadata": null,
            "basic_auth_user": null,
            "basic_auth_pass": null,
            "oauth_client_id": null,
            "oauth_client_secret": null,
            "oauth_token_url": null,
            "oauth_scopes": null,
            "oauth_auth_method": "client_secret_basic",
            "pushToken": null,
            "databaseConnectionString": null,
            "radiusUsername": null,
            "radiusPassword": null,
            "radiusSecret": null,
            "mqttUsername": "",
            "mqttPassword": "",
            "authWorkstation": null,
            "authDomain": null,
            "tlsCa": null,
            "tlsCert": null,
            "tlsKey": null,
            "kafkaProducerSaslOptions": {
                "mechanism": "None"
            },
            "includeSensitiveData": true
        },
        {
            "id": 10,
            "name": "官网-ANSTIQUE",
            "description": null,
            "pathName": "官网-ANSTIQUE",
            "parent": null,
            "childrenIDs": [],
            "url": "https://anstique.com/chat",
            "method": "GET",
            "hostname": null,
            "port": null,
            "maxretries": 0,
            "weight": 2000,
            "active": true,
            "forceInactive": false,
            "type": "http",
            "timeout": 48,
            "interval": 60,
            "retryInterval": 60,
            "resendInterval": 0,
            "keyword": null,
            "invertKeyword": false,
            "expiryNotification": false,
            "ignoreTls": false,
            "upsideDown": false,
            "packetSize": 56,
            "maxredirects": 10,
            "accepted_statuscodes": [
                "200-299"
            ],
            "dns_resolve_type": "A",
            "dns_resolve_server": "1.1.1.1",
            "dns_last_result": null,
            "docker_container": "",
            "docker_host": null,
            "proxyId": null,
            "notificationIDList": {},
            "tags": [],
            "maintenance": false,
            "mqttTopic": "",
            "mqttSuccessMessage": "",
            "databaseQuery": null,
            "authMethod": null,
            "grpcUrl": null,
            "grpcProtobuf": null,
            "grpcMethod": null,
            "grpcServiceName": null,
            "grpcEnableTls": false,
            "radiusCalledStationId": null,
            "radiusCallingStationId": null,
            "game": null,
            "gamedigGivenPortOnly": true,
            "httpBodyEncoding": "json",
            "jsonPath": null,
            "expectedValue": null,
            "kafkaProducerTopic": null,
            "kafkaProducerBrokers": [],
            "kafkaProducerSsl": false,
            "kafkaProducerAllowAutoTopicCreation": false,
            "kafkaProducerMessage": null,
            "screenshot": null,
            "headers": null,
            "body": null,
            "grpcBody": null,
            "grpcMetadata": null,
            "basic_auth_user": null,
            "basic_auth_pass": null,
            "oauth_client_id": null,
            "oauth_client_secret": null,
            "oauth_token_url": null,
            "oauth_scopes": null,
            "oauth_auth_method": "client_secret_basic",
            "pushToken": null,
            "databaseConnectionString": null,
            "radiusUsername": null,
            "radiusPassword": null,
            "radiusSecret": null,
            "mqttUsername": "",
            "mqttPassword": "",
            "authWorkstation": null,
            "authDomain": null,
            "tlsCa": null,
            "tlsCert": null,
            "tlsKey": null,
            "kafkaProducerSaslOptions": {
                "mechanism": "None"
            },
            "includeSensitiveData": true
        }
    ]
}